{
  "page": 18,
  "chapter": 14,
  "chapterTitle": "Still Here",
  "bookId": "whereWeFirstMet",
  "blocks": [
    { "type": "narration", "content": "After." },
    { "type": "narration", "content": "After the crying. After the quiet that followed it." },
    { "type": "narration", "content": "He sat back up. Wiped his face. Didn't apologize for any of it." },
    { "type": "dialogue", "speaker": "Cassandra", "content": "Tell me what happened." },
    { "type": "narration", "content": "He looked at her." },
    { "type": "dialogue", "speaker": "Cassandra", "content": "From your side. I want to hear it from you." },
    { "type": "narration", "content": "So he told her. The dinner table. The way she stopped mid-sentence. How fast it happened — the color draining from her face, the chair, the floor. What his hands had felt like on the way around the table. What her face had looked like." },
    { "type": "narration", "content": "She listened without moving." },
    { "type": "dialogue", "speaker": "Ethan", "content": "Lena called 911. She's the one who kept it together." },
    { "type": "dialogue", "speaker": "Cassandra", "content": "That sounds like Lena." },
    { "type": "dialogue", "speaker": "Ethan", "content": "She was extraordinary." },
    { "type": "narration", "content": "A pause." },
    { "type": "dialogue", "speaker": "Cassandra", "content": "My dad?" },
    { "type": "dialogue", "speaker": "Ethan", "content": "He's out there. They all are. Your mom, Maya, Nathan. Lena." },
    { "type": "narration", "content": "She closed her eyes." },
    { "type": "dialogue", "speaker": "Cassandra", "content": "Tell my dad first. Tell him I'm okay." },
    { "type": "dialogue", "speaker": "Ethan", "content": "I will." },
    { "type": "narration", "content": "She was quiet for a moment. He waited." },
    { "type": "dialogue", "speaker": "Cassandra", "content": "Were you scared?" },
    { "type": "narration", "content": "He looked at her directly." },
    { "type": "dialogue", "speaker": "Ethan", "content": "I thought — for a moment I thought I was watching you—" },
    { "type": "narration", "content": "He stopped. Couldn't finish it." },
    { "type": "narration", "content": "She squeezed his hand." },
    { "type": "dialogue", "speaker": "Cassandra", "content": "I know." },
    { "type": "dialogue", "speaker": "Ethan", "content": "I need you to understand that for me, in those six minutes, everything I—" },
    { "type": "narration", "content": "He stopped again. Looked at the window. The dark glass. His own reflection in it." },
    { "type": "dialogue", "speaker": "Ethan", "content": "You are every good thing in my life. You understand that? Everything good that I have is because of you and I don't say it enough and I should say it more." },
    { "type": "narration", "content": "She was very still." },
    { "type": "narration", "content": "She reached up and touched his face. Her hand against his cheek." },
    { "type": "dialogue", "speaker": "Cassandra", "content": "I know." },
    { "type": "dialogue", "speaker": "Cassandra", "content": "I'm still here, Ethan." },
    { "type": "narration", "content": "He turned his face into her hand for just a second. Then he straightened." },
    { "type": "dialogue", "speaker": "Ethan", "content": "I'm going to go tell your dad." },
    { "type": "dialogue", "speaker": "Cassandra", "content": "Okay." },
    { "type": "narration", "content": "He stood. He was halfway to the door." },
    { "type": "dialogue", "speaker": "Cassandra", "content": "Ethan." },
    { "type": "narration", "content": "He stopped. Turned." },
    { "type": "dialogue", "speaker": "Cassandra", "content": "Come back." },
    { "type": "dialogue", "speaker": "Ethan", "content": "I'm always going to come back." }
  ]
}
