{
  "page": 1,
  "chapter": 6,
  "chapterTitle": "Somebody",
  "bookId": "firefliesBetweenUs",
  "blocks": [
    { "type": "narration", "content": "Millhaven High School was three times the size of the middle school. Bigger hallways, bigger classes, upperclassmen who moved through the building like they owned it." },
    { "type": "narration", "content": "Daisy, predictably, had already figured out where everything was." },
    { "type": "dialogue", "speaker": "Kit", "content": "How do you know where the gym is." },
    { "type": "dialogue", "speaker": "Daisy", "content": "I looked at the map they sent over the summer." },
    { "type": "dialogue", "speaker": "Kit", "content": "They sent a map?" },
    { "type": "dialogue", "speaker": "Daisy", "content": "Kit." },
    { "type": "dialogue", "speaker": "Kit", "content": "I didn't read everything they sent." },
    { "type": "dialogue", "speaker": "Daisy", "content": "I know you didn't." },
    { "type": "narration", "content": "She steered him left at the junction by the library and they found their homeroom with four minutes to spare." },
    { "type": "dialogue", "speaker": "Daisy", "content": "Read the things they send you." },
    { "type": "dialogue", "speaker": "Kit", "content": "I have you." },
    { "type": "narration", "content": "She shook her head and went to find a seat. He sat next to her." },
    { "type": "internalThought", "speaker": "Kit", "content": "Okay. High school. We can do this." }
  ]
}
